Metadata-Version: 2.4
Name: scahpy
Version: 2.0.10
Summary: SCAHpy — System for Coupled Atmosphere–Hydrosphere Analysis in Python
Author-email: Fiorela Castillón Lucas <fv.castillon@gmail.com>
License-Expression: GPL-3.0-or-later
Project-URL: Homepage, https://github.com/fiorelacl/SCAHpy
Project-URL: Documentation, https://fiorelacl.github.io/SCAHpy/
Project-URL: PyPI, https://pypi.org/project/scahpy/
Keywords: scahpy,xarray,climate,WRF,CROCO,ocean-atmosphere
Classifier: Programming Language :: Python :: 3
Classifier: Programming Language :: Python :: 3.11
Classifier: Intended Audience :: Science/Research
Classifier: Topic :: Scientific/Engineering :: Atmospheric Science
Classifier: Topic :: Scientific/Engineering :: Oceanography
Requires-Python: >=3.10
License-File: LICENSE
Requires-Dist: netCDF4
Requires-Dist: xarray
Requires-Dist: dask
Requires-Dist: numpy
Requires-Dist: pandas
Requires-Dist: matplotlib
Requires-Dist: cartopy
Requires-Dist: cmocean
Requires-Dist: cmcrameri
Requires-Dist: pyshp
Dynamic: license-file
